{
  "products": [
    {
      "id": 1,
      "name": "Caneta BIC preta",
      "price": 5.89
    },
    {
      "id": 2,
      "name": "Notebook Asus Vivobook",
      "price": 5400
    },
    {
      "id": 3,
      "name": "Samsung S20+",
      "price": 4800
    },
    {
      "id": 4,
      "name": "Paçoca",
      "price": 0.3
    },
    {
      "name": "Teste",
      "price": "1.98",
      "id": 16
    },
    {
      "name": "Caneta Faber Castel",
      "price": "1.50",
      "id": 17
    }
  ]
}